{
  "last_updated": "2026-07-22T08:45:02.556416Z",
  "scan_results": [
    {
      "ticker": "CHAI",
      "name": "Core AI Holdings Inc",
      "status": "ALERT",
      "source": "regular",
      "price": 0.681,
      "change_pct": 74.39180537772087,
      "volume": 13081934,
      "market_cap": 8548765.86,
      "float_shares": 8964178,
      "country": "Canada",
      "scan_reason": "Passed filters",
      "scan_passed": true,
      "result": "+74.4% \u00b7 Entry $0.68 \u00b7 T1 $0.71 \u00b7 T2 $0.72 \u00b7 T3 $0.75",
      "plan": {
        "valid": true,
        "ticker": "CHAI",
        "entry": 0.681,
        "stop": 0.6674,
        "targets": {
          "t1": 0.7082,
          "t2": 0.7218,
          "t3": 0.749
        },
        "risk_per_share": 0.0136,
        "risk_amount": 100.0,
        "daily_risk_budget": 300.0,
        "risk_unit_label": "R = $100.0 (3% daily \u00f7 3 trades)",
        "shares": 3671,
        "position_value": 2499.95,
        "risk_reward": 2.0,
        "confidence": "MED",
        "strategy": "Demand zone + candlestick confirmation scalp",
        "exit_rules": {
          "momentum_based": true,
          "time_based": false,
          "trail_breakeven_at": "+1%",
          "hard_stop": "$0.6674"
        }
      },
      "ta": {
        "valid": false,
        "error": "No bar data"
      },
      "news": {
        "ticker": "CHAI",
        "total_items": 20,
        "scored_items": [
          {
            "title": "Core AI Holdings (CHAI) Stock Rallies Nearly 132% After Hours: Here's Why it is Trending",
            "source": "Webull",
            "time": "3h ago \u00b7 22 Jul",
            "raw_time": "2026-07-22T05:28:11.000+0000",
            "url": "",
            "score": 0,
            "keywords": []
          },
          {
            "title": "Core AI Holdings Elevates HomeGPT as AI Residential Decision Layer Amid Shifting U.S. Housing Market",
            "source": "Webull",
            "time": "19h ago \u00b7 21 Jul",
            "raw_time": "2026-07-21T13:29:50.000+0000",
            "url": "",
            "score": 0,
            "keywords": []
          },
          {
            "title": "Core AI Holdings expands positioning of HomeGPT",
            "source": "Webull",
            "time": "19h ago \u00b7 21 Jul",
            "raw_time": "2026-07-21T12:55:28.000+0000",
            "url": "",
            "score": 0,
            "keywords": []
          },
          {
            "title": "Core AI Holdings Expanding HomeGPT Role Beyond Home Visualization For Planning, Renovation, Residential Buying Decisions",
            "source": "Webull",
            "time": "20h ago \u00b7 21 Jul",
            "raw_time": "2026-07-21T12:16:55.000+0000",
            "url": "",
            "score": 0,
            "keywords": []
          },
          {
            "title": "Core AI Holdings Advances AI Powered Residential Decision Intelligence",
            "source": "Webull",
            "time": "1d ago \u00b7 21 Jul",
            "raw_time": "2026-07-21T07:15:00.000+0000",
            "url": "",
            "score": 0,
            "keywords": []
          },
          {
            "title": "12 Information Technology Stocks Moving In Monday's Pre-Market Session",
            "source": "Webull",
            "time": "1d ago \u00b7 20 Jul",
            "raw_time": "2026-07-20T12:05:32.000+0000",
            "url": "",
            "score": 0,
            "keywords": []
          },
          {
            "title": "Weekly Report: what happened at CHAI last week (0713-0717)?",
            "source": "Webull",
            "time": "1d ago \u00b7 20 Jul",
            "raw_time": "2026-07-20T09:59:59.389+0000",
            "url": "",
            "score": 0,
            "keywords": []
          },
          {
            "title": "12 Information Technology Stocks Moving In Friday's After-Market Session",
            "source": "Webull",
            "time": "4d ago \u00b7 17 Jul",
            "raw_time": "2026-07-17T21:05:43.000+0000",
            "url": "",
            "score": 0,
            "keywords": []
          },
          {
            "title": "Core AI Holdings CFO Arie Gordashnikov files initial beneficial ownership statement",
            "source": "Webull",
            "time": "5d ago \u00b7 16 Jul",
            "raw_time": "2026-07-16T20:03:20.000+0000",
            "url": "",
            "score": 0,
            "keywords": []
          }
        ],
        "headlines": [
          {
            "title": "Core AI Holdings (CHAI) Stock Rallies Nearly 132% After Hours: Here's Why it is Trending",
            "source": "Webull",
            "time": "3h ago \u00b7 22 Jul",
            "raw_time": "2026-07-22T05:28:11.000+0000",
            "url": "",
            "score": 0,
            "keywords": []
          },
          {
            "title": "Core AI Holdings Elevates HomeGPT as AI Residential Decision Layer Amid Shifting U.S. Housing Market",
            "source": "Webull",
            "time": "19h ago \u00b7 21 Jul",
            "raw_time": "2026-07-21T13:29:50.000+0000",
            "url": "",
            "score": 0,
            "keywords": []
          },
          {
            "title": "Core AI Holdings expands positioning of HomeGPT",
            "source": "Webull",
            "time": "19h ago \u00b7 21 Jul",
            "raw_time": "2026-07-21T12:55:28.000+0000",
            "url": "",
            "score": 0,
            "keywords": []
          },
          {
            "title": "Core AI Holdings Expanding HomeGPT Role Beyond Home Visualization For Planning, Renovation, Residential Buying Decisions",
            "source": "Webull",
            "time": "20h ago \u00b7 21 Jul",
            "raw_time": "2026-07-21T12:16:55.000+0000",
            "url": "",
            "score": 0,
            "keywords": []
          },
          {
            "title": "Core AI Holdings Advances AI Powered Residential Decision Intelligence",
            "source": "Webull",
            "time": "1d ago \u00b7 21 Jul",
            "raw_time": "2026-07-21T07:15:00.000+0000",
            "url": "",
            "score": 0,
            "keywords": []
          },
          {
            "title": "12 Information Technology Stocks Moving In Monday's Pre-Market Session",
            "source": "Webull",
            "time": "1d ago \u00b7 20 Jul",
            "raw_time": "2026-07-20T12:05:32.000+0000",
            "url": "",
            "score": 0,
            "keywords": []
          },
          {
            "title": "Weekly Report: what happened at CHAI last week (0713-0717)?",
            "source": "Webull",
            "time": "1d ago \u00b7 20 Jul",
            "raw_time": "2026-07-20T09:59:59.389+0000",
            "url": "",
            "score": 0,
            "keywords": []
          },
          {
            "title": "12 Information Technology Stocks Moving In Friday's After-Market Session",
            "source": "Webull",
            "time": "4d ago \u00b7 17 Jul",
            "raw_time": "2026-07-17T21:05:43.000+0000",
            "url": "",
            "score": 0,
            "keywords": []
          },
          {
            "title": "Core AI Holdings CFO Arie Gordashnikov files initial beneficial ownership statement",
            "source": "Webull",
            "time": "5d ago \u00b7 16 Jul",
            "raw_time": "2026-07-16T20:03:20.000+0000",
            "url": "",
            "score": 0,
            "keywords": []
          }
        ],
        "red_flags": [],
        "max_score": 0,
        "avg_score": 0.0,
        "catalyst_confirmed": false,
        "high_impact_count": 0,
        "top_headline": "Core AI Holdings (CHAI) Stock Rallies Nearly 132% After Hours: Here's Why it is Trending",
        "news_filter_reason": "low catalyst score (max 0/5)"
      },
      "tape": {
        "ticker": "CHAI",
        "valid": true,
        "stale": false,
        "no_move": false,
        "tape_score": 8.0,
        "rvol": 2.44,
        "volume_indicator": "high",
        "volume": 13081934,
        "adv": 5363869,
        "recent_pct_of_adv": 243.89,
        "volume_acceleration": 0.0,
        "price_velocity_pct": 0.0,
        "buy_pressure_pct": 0.0,
        "large_bar_count": 0,
        "vwap_distance_pct": 0.0,
        "recent_volume": 13081934,
        "prior_volume": 0,
        "median_range": 0.0,
        "last_price": 0.3905,
        "vwap": null,
        "last_trade_time": "2026-07-22T08:44:18.805000+00:00",
        "stale_age_seconds": 38
      },
      "date": "2026-07-22",
      "time": "18:44:57",
      "skip_news_check": false
    },
    {
      "ticker": "INLF",
      "name": "INLIF",
      "status": "ALERT",
      "source": "regular",
      "price": 4.587,
      "change_pct": 105.69506726457398,
      "volume": 2305995,
      "market_cap": 2439062.5,
      "float_shares": 978465,
      "country": "China / Cayman-China",
      "scan_reason": "Passed filters",
      "scan_passed": true,
      "result": "+105.7% \u00b7 Entry $4.59 \u00b7 T1 $4.77 \u00b7 T2 $4.86 \u00b7 T3 $5.05",
      "plan": {
        "valid": true,
        "ticker": "INLF",
        "entry": 4.587,
        "stop": 4.4953,
        "targets": {
          "t1": 4.7704,
          "t2": 4.8621,
          "t3": 5.0455
        },
        "risk_per_share": 0.0917,
        "risk_amount": 100.0,
        "daily_risk_budget": 300.0,
        "risk_unit_label": "R = $100.0 (3% daily \u00f7 3 trades)",
        "shares": 545,
        "position_value": 2499.91,
        "risk_reward": 2.0,
        "confidence": "MED",
        "strategy": "Demand zone + candlestick confirmation scalp",
        "exit_rules": {
          "momentum_based": true,
          "time_based": false,
          "trail_breakeven_at": "+1%",
          "hard_stop": "$4.4953"
        }
      },
      "ta": {
        "valid": false,
        "error": "No bar data"
      },
      "news": {
        "ticker": "INLF",
        "total_items": 20,
        "scored_items": [
          {
            "title": "Weekly Report: what happened at INLF last week (0713-0717)?",
            "source": "Webull",
            "time": "1d ago \u00b7 20 Jul",
            "raw_time": "2026-07-20T10:00:53.061+0000",
            "url": "",
            "score": 0,
            "keywords": []
          }
        ],
        "headlines": [
          {
            "title": "Weekly Report: what happened at INLF last week (0713-0717)?",
            "source": "Webull",
            "time": "1d ago \u00b7 20 Jul",
            "raw_time": "2026-07-20T10:00:53.061+0000",
            "url": "",
            "score": 0,
            "keywords": []
          }
        ],
        "red_flags": [],
        "max_score": 0,
        "avg_score": 0.0,
        "catalyst_confirmed": false,
        "high_impact_count": 0,
        "top_headline": "Weekly Report: what happened at INLF last week (0713-0717)?",
        "news_filter_reason": "low catalyst score (max 0/5)"
      },
      "tape": {
        "ticker": "INLF",
        "valid": true,
        "stale": false,
        "no_move": false,
        "tape_score": 8.0,
        "rvol": 3.87,
        "volume_indicator": "high",
        "volume": 2305995,
        "adv": 596191,
        "recent_pct_of_adv": 386.79,
        "volume_acceleration": 0.0,
        "price_velocity_pct": 0.0,
        "buy_pressure_pct": 0.0,
        "large_bar_count": 0,
        "vwap_distance_pct": 0.0,
        "recent_volume": 2305995,
        "prior_volume": 0,
        "median_range": 0.0,
        "last_price": 2.23,
        "vwap": null,
        "last_trade_time": "2026-07-22T08:44:18.838000+00:00",
        "stale_age_seconds": 38
      },
      "date": "2026-07-22",
      "time": "18:44:57",
      "skip_news_check": false
    }
  ],
  "pre_market_results": [
    {
      "ticker": "CHAI",
      "name": "Core AI Holdings Inc",
      "status": "ALERT",
      "source": "regular",
      "price": 0.681,
      "change_pct": 74.39180537772087,
      "volume": 13081934,
      "market_cap": 8548765.86,
      "float_shares": 8964178,
      "country": "Canada",
      "scan_reason": "Passed filters",
      "scan_passed": true,
      "result": "+74.4% \u00b7 Entry $0.68 \u00b7 T1 $0.71 \u00b7 T2 $0.72 \u00b7 T3 $0.75",
      "plan": {
        "valid": true,
        "ticker": "CHAI",
        "entry": 0.681,
        "stop": 0.6674,
        "targets": {
          "t1": 0.7082,
          "t2": 0.7218,
          "t3": 0.749
        },
        "risk_per_share": 0.0136,
        "risk_amount": 100.0,
        "daily_risk_budget": 300.0,
        "risk_unit_label": "R = $100.0 (3% daily \u00f7 3 trades)",
        "shares": 3671,
        "position_value": 2499.95,
        "risk_reward": 2.0,
        "confidence": "MED",
        "strategy": "Demand zone + candlestick confirmation scalp",
        "exit_rules": {
          "momentum_based": true,
          "time_based": false,
          "trail_breakeven_at": "+1%",
          "hard_stop": "$0.6674"
        }
      },
      "ta": {
        "valid": false,
        "error": "No bar data"
      },
      "news": {
        "ticker": "CHAI",
        "total_items": 20,
        "scored_items": [
          {
            "title": "Core AI Holdings (CHAI) Stock Rallies Nearly 132% After Hours: Here's Why it is Trending",
            "source": "Webull",
            "time": "3h ago \u00b7 22 Jul",
            "raw_time": "2026-07-22T05:28:11.000+0000",
            "url": "",
            "score": 0,
            "keywords": []
          },
          {
            "title": "Core AI Holdings Elevates HomeGPT as AI Residential Decision Layer Amid Shifting U.S. Housing Market",
            "source": "Webull",
            "time": "19h ago \u00b7 21 Jul",
            "raw_time": "2026-07-21T13:29:50.000+0000",
            "url": "",
            "score": 0,
            "keywords": []
          },
          {
            "title": "Core AI Holdings expands positioning of HomeGPT",
            "source": "Webull",
            "time": "19h ago \u00b7 21 Jul",
            "raw_time": "2026-07-21T12:55:28.000+0000",
            "url": "",
            "score": 0,
            "keywords": []
          },
          {
            "title": "Core AI Holdings Expanding HomeGPT Role Beyond Home Visualization For Planning, Renovation, Residential Buying Decisions",
            "source": "Webull",
            "time": "20h ago \u00b7 21 Jul",
            "raw_time": "2026-07-21T12:16:55.000+0000",
            "url": "",
            "score": 0,
            "keywords": []
          },
          {
            "title": "Core AI Holdings Advances AI Powered Residential Decision Intelligence",
            "source": "Webull",
            "time": "1d ago \u00b7 21 Jul",
            "raw_time": "2026-07-21T07:15:00.000+0000",
            "url": "",
            "score": 0,
            "keywords": []
          },
          {
            "title": "12 Information Technology Stocks Moving In Monday's Pre-Market Session",
            "source": "Webull",
            "time": "1d ago \u00b7 20 Jul",
            "raw_time": "2026-07-20T12:05:32.000+0000",
            "url": "",
            "score": 0,
            "keywords": []
          },
          {
            "title": "Weekly Report: what happened at CHAI last week (0713-0717)?",
            "source": "Webull",
            "time": "1d ago \u00b7 20 Jul",
            "raw_time": "2026-07-20T09:59:59.389+0000",
            "url": "",
            "score": 0,
            "keywords": []
          },
          {
            "title": "12 Information Technology Stocks Moving In Friday's After-Market Session",
            "source": "Webull",
            "time": "4d ago \u00b7 17 Jul",
            "raw_time": "2026-07-17T21:05:43.000+0000",
            "url": "",
            "score": 0,
            "keywords": []
          },
          {
            "title": "Core AI Holdings CFO Arie Gordashnikov files initial beneficial ownership statement",
            "source": "Webull",
            "time": "5d ago \u00b7 16 Jul",
            "raw_time": "2026-07-16T20:03:20.000+0000",
            "url": "",
            "score": 0,
            "keywords": []
          }
        ],
        "headlines": [
          {
            "title": "Core AI Holdings (CHAI) Stock Rallies Nearly 132% After Hours: Here's Why it is Trending",
            "source": "Webull",
            "time": "3h ago \u00b7 22 Jul",
            "raw_time": "2026-07-22T05:28:11.000+0000",
            "url": "",
            "score": 0,
            "keywords": []
          },
          {
            "title": "Core AI Holdings Elevates HomeGPT as AI Residential Decision Layer Amid Shifting U.S. Housing Market",
            "source": "Webull",
            "time": "19h ago \u00b7 21 Jul",
            "raw_time": "2026-07-21T13:29:50.000+0000",
            "url": "",
            "score": 0,
            "keywords": []
          },
          {
            "title": "Core AI Holdings expands positioning of HomeGPT",
            "source": "Webull",
            "time": "19h ago \u00b7 21 Jul",
            "raw_time": "2026-07-21T12:55:28.000+0000",
            "url": "",
            "score": 0,
            "keywords": []
          },
          {
            "title": "Core AI Holdings Expanding HomeGPT Role Beyond Home Visualization For Planning, Renovation, Residential Buying Decisions",
            "source": "Webull",
            "time": "20h ago \u00b7 21 Jul",
            "raw_time": "2026-07-21T12:16:55.000+0000",
            "url": "",
            "score": 0,
            "keywords": []
          },
          {
            "title": "Core AI Holdings Advances AI Powered Residential Decision Intelligence",
            "source": "Webull",
            "time": "1d ago \u00b7 21 Jul",
            "raw_time": "2026-07-21T07:15:00.000+0000",
            "url": "",
            "score": 0,
            "keywords": []
          },
          {
            "title": "12 Information Technology Stocks Moving In Monday's Pre-Market Session",
            "source": "Webull",
            "time": "1d ago \u00b7 20 Jul",
            "raw_time": "2026-07-20T12:05:32.000+0000",
            "url": "",
            "score": 0,
            "keywords": []
          },
          {
            "title": "Weekly Report: what happened at CHAI last week (0713-0717)?",
            "source": "Webull",
            "time": "1d ago \u00b7 20 Jul",
            "raw_time": "2026-07-20T09:59:59.389+0000",
            "url": "",
            "score": 0,
            "keywords": []
          },
          {
            "title": "12 Information Technology Stocks Moving In Friday's After-Market Session",
            "source": "Webull",
            "time": "4d ago \u00b7 17 Jul",
            "raw_time": "2026-07-17T21:05:43.000+0000",
            "url": "",
            "score": 0,
            "keywords": []
          },
          {
            "title": "Core AI Holdings CFO Arie Gordashnikov files initial beneficial ownership statement",
            "source": "Webull",
            "time": "5d ago \u00b7 16 Jul",
            "raw_time": "2026-07-16T20:03:20.000+0000",
            "url": "",
            "score": 0,
            "keywords": []
          }
        ],
        "red_flags": [],
        "max_score": 0,
        "avg_score": 0.0,
        "catalyst_confirmed": false,
        "high_impact_count": 0,
        "top_headline": "Core AI Holdings (CHAI) Stock Rallies Nearly 132% After Hours: Here's Why it is Trending",
        "news_filter_reason": "low catalyst score (max 0/5)"
      },
      "tape": {
        "ticker": "CHAI",
        "valid": true,
        "stale": false,
        "no_move": false,
        "tape_score": 8.0,
        "rvol": 2.44,
        "volume_indicator": "high",
        "volume": 13081934,
        "adv": 5363869,
        "recent_pct_of_adv": 243.89,
        "volume_acceleration": 0.0,
        "price_velocity_pct": 0.0,
        "buy_pressure_pct": 0.0,
        "large_bar_count": 0,
        "vwap_distance_pct": 0.0,
        "recent_volume": 13081934,
        "prior_volume": 0,
        "median_range": 0.0,
        "last_price": 0.3905,
        "vwap": null,
        "last_trade_time": "2026-07-22T08:44:18.805000+00:00",
        "stale_age_seconds": 38
      },
      "date": "2026-07-22",
      "time": "18:44:57",
      "skip_news_check": false
    },
    {
      "ticker": "INLF",
      "name": "INLIF",
      "status": "ALERT",
      "source": "regular",
      "price": 4.587,
      "change_pct": 105.69506726457398,
      "volume": 2305995,
      "market_cap": 2439062.5,
      "float_shares": 978465,
      "country": "China / Cayman-China",
      "scan_reason": "Passed filters",
      "scan_passed": true,
      "result": "+105.7% \u00b7 Entry $4.59 \u00b7 T1 $4.77 \u00b7 T2 $4.86 \u00b7 T3 $5.05",
      "plan": {
        "valid": true,
        "ticker": "INLF",
        "entry": 4.587,
        "stop": 4.4953,
        "targets": {
          "t1": 4.7704,
          "t2": 4.8621,
          "t3": 5.0455
        },
        "risk_per_share": 0.0917,
        "risk_amount": 100.0,
        "daily_risk_budget": 300.0,
        "risk_unit_label": "R = $100.0 (3% daily \u00f7 3 trades)",
        "shares": 545,
        "position_value": 2499.91,
        "risk_reward": 2.0,
        "confidence": "MED",
        "strategy": "Demand zone + candlestick confirmation scalp",
        "exit_rules": {
          "momentum_based": true,
          "time_based": false,
          "trail_breakeven_at": "+1%",
          "hard_stop": "$4.4953"
        }
      },
      "ta": {
        "valid": false,
        "error": "No bar data"
      },
      "news": {
        "ticker": "INLF",
        "total_items": 20,
        "scored_items": [
          {
            "title": "Weekly Report: what happened at INLF last week (0713-0717)?",
            "source": "Webull",
            "time": "1d ago \u00b7 20 Jul",
            "raw_time": "2026-07-20T10:00:53.061+0000",
            "url": "",
            "score": 0,
            "keywords": []
          }
        ],
        "headlines": [
          {
            "title": "Weekly Report: what happened at INLF last week (0713-0717)?",
            "source": "Webull",
            "time": "1d ago \u00b7 20 Jul",
            "raw_time": "2026-07-20T10:00:53.061+0000",
            "url": "",
            "score": 0,
            "keywords": []
          }
        ],
        "red_flags": [],
        "max_score": 0,
        "avg_score": 0.0,
        "catalyst_confirmed": false,
        "high_impact_count": 0,
        "top_headline": "Weekly Report: what happened at INLF last week (0713-0717)?",
        "news_filter_reason": "low catalyst score (max 0/5)"
      },
      "tape": {
        "ticker": "INLF",
        "valid": true,
        "stale": false,
        "no_move": false,
        "tape_score": 8.0,
        "rvol": 3.87,
        "volume_indicator": "high",
        "volume": 2305995,
        "adv": 596191,
        "recent_pct_of_adv": 386.79,
        "volume_acceleration": 0.0,
        "price_velocity_pct": 0.0,
        "buy_pressure_pct": 0.0,
        "large_bar_count": 0,
        "vwap_distance_pct": 0.0,
        "recent_volume": 2305995,
        "prior_volume": 0,
        "median_range": 0.0,
        "last_price": 2.23,
        "vwap": null,
        "last_trade_time": "2026-07-22T08:44:18.838000+00:00",
        "stale_age_seconds": 38
      },
      "date": "2026-07-22",
      "time": "18:44:57",
      "skip_news_check": false
    }
  ],
  "pre_market_watchlist": [],
  "bounce_results": [],
  "losers_scanned": 50,
  "active_plan": {
    "ticker": "CHAI",
    "name": "Core AI Holdings Inc",
    "status": "ALERT",
    "source": "regular",
    "price": 0.681,
    "change_pct": 74.39180537772087,
    "volume": 13081934,
    "market_cap": 8548765.86,
    "float_shares": 8964178,
    "country": "Canada",
    "scan_reason": "Passed filters",
    "scan_passed": true,
    "result": "+74.4% \u00b7 Entry $0.68 \u00b7 T1 $0.71 \u00b7 T2 $0.72 \u00b7 T3 $0.75",
    "plan": {
      "valid": true,
      "ticker": "CHAI",
      "entry": 0.681,
      "stop": 0.6674,
      "targets": {
        "t1": 0.7082,
        "t2": 0.7218,
        "t3": 0.749
      },
      "risk_per_share": 0.0136,
      "risk_amount": 100.0,
      "daily_risk_budget": 300.0,
      "risk_unit_label": "R = $100.0 (3% daily \u00f7 3 trades)",
      "shares": 3671,
      "position_value": 2499.95,
      "risk_reward": 2.0,
      "confidence": "MED",
      "strategy": "Demand zone + candlestick confirmation scalp",
      "exit_rules": {
        "momentum_based": true,
        "time_based": false,
        "trail_breakeven_at": "+1%",
        "hard_stop": "$0.6674"
      }
    },
    "ta": {
      "valid": false,
      "error": "No bar data"
    },
    "news": {
      "ticker": "CHAI",
      "total_items": 20,
      "scored_items": [
        {
          "title": "Core AI Holdings (CHAI) Stock Rallies Nearly 132% After Hours: Here's Why it is Trending",
          "source": "Webull",
          "time": "3h ago \u00b7 22 Jul",
          "raw_time": "2026-07-22T05:28:11.000+0000",
          "url": "",
          "score": 0,
          "keywords": []
        },
        {
          "title": "Core AI Holdings Elevates HomeGPT as AI Residential Decision Layer Amid Shifting U.S. Housing Market",
          "source": "Webull",
          "time": "19h ago \u00b7 21 Jul",
          "raw_time": "2026-07-21T13:29:50.000+0000",
          "url": "",
          "score": 0,
          "keywords": []
        },
        {
          "title": "Core AI Holdings expands positioning of HomeGPT",
          "source": "Webull",
          "time": "19h ago \u00b7 21 Jul",
          "raw_time": "2026-07-21T12:55:28.000+0000",
          "url": "",
          "score": 0,
          "keywords": []
        },
        {
          "title": "Core AI Holdings Expanding HomeGPT Role Beyond Home Visualization For Planning, Renovation, Residential Buying Decisions",
          "source": "Webull",
          "time": "20h ago \u00b7 21 Jul",
          "raw_time": "2026-07-21T12:16:55.000+0000",
          "url": "",
          "score": 0,
          "keywords": []
        },
        {
          "title": "Core AI Holdings Advances AI Powered Residential Decision Intelligence",
          "source": "Webull",
          "time": "1d ago \u00b7 21 Jul",
          "raw_time": "2026-07-21T07:15:00.000+0000",
          "url": "",
          "score": 0,
          "keywords": []
        },
        {
          "title": "12 Information Technology Stocks Moving In Monday's Pre-Market Session",
          "source": "Webull",
          "time": "1d ago \u00b7 20 Jul",
          "raw_time": "2026-07-20T12:05:32.000+0000",
          "url": "",
          "score": 0,
          "keywords": []
        },
        {
          "title": "Weekly Report: what happened at CHAI last week (0713-0717)?",
          "source": "Webull",
          "time": "1d ago \u00b7 20 Jul",
          "raw_time": "2026-07-20T09:59:59.389+0000",
          "url": "",
          "score": 0,
          "keywords": []
        },
        {
          "title": "12 Information Technology Stocks Moving In Friday's After-Market Session",
          "source": "Webull",
          "time": "4d ago \u00b7 17 Jul",
          "raw_time": "2026-07-17T21:05:43.000+0000",
          "url": "",
          "score": 0,
          "keywords": []
        },
        {
          "title": "Core AI Holdings CFO Arie Gordashnikov files initial beneficial ownership statement",
          "source": "Webull",
          "time": "5d ago \u00b7 16 Jul",
          "raw_time": "2026-07-16T20:03:20.000+0000",
          "url": "",
          "score": 0,
          "keywords": []
        }
      ],
      "headlines": [
        {
          "title": "Core AI Holdings (CHAI) Stock Rallies Nearly 132% After Hours: Here's Why it is Trending",
          "source": "Webull",
          "time": "3h ago \u00b7 22 Jul",
          "raw_time": "2026-07-22T05:28:11.000+0000",
          "url": "",
          "score": 0,
          "keywords": []
        },
        {
          "title": "Core AI Holdings Elevates HomeGPT as AI Residential Decision Layer Amid Shifting U.S. Housing Market",
          "source": "Webull",
          "time": "19h ago \u00b7 21 Jul",
          "raw_time": "2026-07-21T13:29:50.000+0000",
          "url": "",
          "score": 0,
          "keywords": []
        },
        {
          "title": "Core AI Holdings expands positioning of HomeGPT",
          "source": "Webull",
          "time": "19h ago \u00b7 21 Jul",
          "raw_time": "2026-07-21T12:55:28.000+0000",
          "url": "",
          "score": 0,
          "keywords": []
        },
        {
          "title": "Core AI Holdings Expanding HomeGPT Role Beyond Home Visualization For Planning, Renovation, Residential Buying Decisions",
          "source": "Webull",
          "time": "20h ago \u00b7 21 Jul",
          "raw_time": "2026-07-21T12:16:55.000+0000",
          "url": "",
          "score": 0,
          "keywords": []
        },
        {
          "title": "Core AI Holdings Advances AI Powered Residential Decision Intelligence",
          "source": "Webull",
          "time": "1d ago \u00b7 21 Jul",
          "raw_time": "2026-07-21T07:15:00.000+0000",
          "url": "",
          "score": 0,
          "keywords": []
        },
        {
          "title": "12 Information Technology Stocks Moving In Monday's Pre-Market Session",
          "source": "Webull",
          "time": "1d ago \u00b7 20 Jul",
          "raw_time": "2026-07-20T12:05:32.000+0000",
          "url": "",
          "score": 0,
          "keywords": []
        },
        {
          "title": "Weekly Report: what happened at CHAI last week (0713-0717)?",
          "source": "Webull",
          "time": "1d ago \u00b7 20 Jul",
          "raw_time": "2026-07-20T09:59:59.389+0000",
          "url": "",
          "score": 0,
          "keywords": []
        },
        {
          "title": "12 Information Technology Stocks Moving In Friday's After-Market Session",
          "source": "Webull",
          "time": "4d ago \u00b7 17 Jul",
          "raw_time": "2026-07-17T21:05:43.000+0000",
          "url": "",
          "score": 0,
          "keywords": []
        },
        {
          "title": "Core AI Holdings CFO Arie Gordashnikov files initial beneficial ownership statement",
          "source": "Webull",
          "time": "5d ago \u00b7 16 Jul",
          "raw_time": "2026-07-16T20:03:20.000+0000",
          "url": "",
          "score": 0,
          "keywords": []
        }
      ],
      "red_flags": [],
      "max_score": 0,
      "avg_score": 0.0,
      "catalyst_confirmed": false,
      "high_impact_count": 0,
      "top_headline": "Core AI Holdings (CHAI) Stock Rallies Nearly 132% After Hours: Here's Why it is Trending",
      "news_filter_reason": "low catalyst score (max 0/5)"
    },
    "tape": {
      "ticker": "CHAI",
      "valid": true,
      "stale": false,
      "no_move": false,
      "tape_score": 8.0,
      "rvol": 2.44,
      "volume_indicator": "high",
      "volume": 13081934,
      "adv": 5363869,
      "recent_pct_of_adv": 243.89,
      "volume_acceleration": 0.0,
      "price_velocity_pct": 0.0,
      "buy_pressure_pct": 0.0,
      "large_bar_count": 0,
      "vwap_distance_pct": 0.0,
      "recent_volume": 13081934,
      "prior_volume": 0,
      "median_range": 0.0,
      "last_price": 0.3905,
      "vwap": null,
      "last_trade_time": "2026-07-22T08:44:18.805000+00:00",
      "stale_age_seconds": 38
    },
    "date": "2026-07-22",
    "time": "18:44:57",
    "skip_news_check": false
  },
  "total_candidates": 2,
  "alerts_generated": 2,
  "all_gainers": [
    {
      "ticker": "INLF",
      "name": "INLIF",
      "price": 4.587,
      "change_pct": 105.69506726457398,
      "volume": 2305995,
      "rvol": 0.0,
      "market_cap": 2439062.5,
      "float_shares": 978465,
      "passed": true,
      "reason": "Passed filters"
    },
    {
      "ticker": "CHAI",
      "name": "Core AI Holdings Inc",
      "price": 0.681,
      "change_pct": 74.39180537772087,
      "volume": 13081934,
      "rvol": 0.0,
      "market_cap": 8548765.86,
      "float_shares": 8964178,
      "passed": true,
      "reason": "Passed filters"
    },
    {
      "ticker": "ZCMD",
      "name": "Zhongchao Inc",
      "price": 2.487,
      "change_pct": 69.18367346938777,
      "volume": 2137351,
      "rvol": 0.0,
      "market_cap": 1700122.62,
      "float_shares": 1145870,
      "passed": false,
      "reason": "Filtered: tiny avg $vol"
    },
    {
      "ticker": "LICN",
      "name": "Lichen International",
      "price": 1.77,
      "change_pct": 53.91304347826088,
      "volume": 2576696,
      "rvol": 0.0,
      "market_cap": 18902348.75,
      "float_shares": 16325300,
      "passed": false,
      "reason": "Filtered: vol/float 0.16x < 0.5x"
    },
    {
      "ticker": "SXTC",
      "name": "China Sxt Pharmaceuticals Inc",
      "price": 4.066,
      "change_pct": 51.716417910447745,
      "volume": 2833037,
      "rvol": 0.0,
      "market_cap": 102424446.36,
      "float_shares": 37944871,
      "passed": false,
      "reason": "Filtered: vol/float 0.07x < 0.5x"
    },
    {
      "ticker": "AEHL",
      "name": "Antelope Enterprise Hldgs Ltd",
      "price": 0.827,
      "change_pct": 28.097893432465927,
      "volume": 2659795,
      "rvol": 0.0,
      "market_cap": 11719218.49,
      "float_shares": 15572001,
      "passed": false,
      "reason": "Filtered: vol/float 0.17x < 0.5x"
    },
    {
      "ticker": "ZBAO",
      "name": "Zhibao Tech",
      "price": 0.231,
      "change_pct": 27.624309392265207,
      "volume": 1933889,
      "rvol": 0.0,
      "market_cap": 6165166.25,
      "float_shares": 8766787,
      "passed": false,
      "reason": "Filtered: tiny rvol 0.4x, tiny vol/float 0.22x, vol/float 0.22x < 0.5x"
    },
    {
      "ticker": "FNWD",
      "name": "Finward Bancorp",
      "price": 43.0,
      "change_pct": 17.8405042477391,
      "volume": 80,
      "rvol": 0.0,
      "market_cap": 158000641.79,
      "float_shares": 3388519,
      "passed": false,
      "reason": "Filtered: vol 80, vol/float 0.00x < 0.5x, avg $vol $0.3M < $0.5M"
    },
    {
      "ticker": "LSE",
      "name": "LEISHEN ENERGY HLDG CO LTD",
      "price": 5.16,
      "change_pct": 17.8082191780822,
      "volume": 31,
      "rvol": 0.0,
      "market_cap": 74569500.0,
      "float_shares": 1525000,
      "passed": false,
      "reason": "Filtered: vol 31, vol/float 0.00x < 0.5x, avg $vol $0.0M < $0.5M"
    },
    {
      "ticker": "SMCI",
      "name": "Super Micro Computer Inc",
      "price": 29.47,
      "change_pct": 15.568627450980388,
      "volume": 658913,
      "rvol": 0.0,
      "market_cap": 16494225613.5,
      "float_shares": 563450031,
      "passed": false,
      "reason": "Filtered: mktcap $16494.2M, float 563.5M > 100M, vol/float 0.00x < 0.5x"
    },
    {
      "ticker": "AIRJ",
      "name": "Airjoule Technologies Corp",
      "price": 4.31,
      "change_pct": 14.323607427055693,
      "volume": 10492,
      "rvol": 0.0,
      "market_cap": 272950216.76,
      "float_shares": 36364362,
      "passed": false,
      "reason": "Filtered: vol 10,492, vol/float 0.00x < 0.5x"
    },
    {
      "ticker": "EZRA",
      "name": "Reliance Global Group Inc",
      "price": 2.59,
      "change_pct": 13.1004366812227,
      "volume": 13623,
      "rvol": 0.0,
      "market_cap": 1272699.56,
      "float_shares": 514897,
      "passed": false,
      "reason": "Filtered: tiny rvol 0.1x, tiny avg $vol, tiny vol/float 0.03x, vol 13,623, vol/float 0.03x < 0.5x, avg $vol $0.2M < $0.5M"
    },
    {
      "ticker": "JG",
      "name": "Aurora Mobile Limited",
      "price": 4.38,
      "change_pct": 12.59640102827763,
      "volume": 75,
      "rvol": 0.0,
      "market_cap": 23193607.63,
      "float_shares": 4207165,
      "passed": false,
      "reason": "Filtered: vol 75, vol/float 0.00x < 0.5x, avg $vol $0.0M < $0.5M"
    },
    {
      "ticker": "MPU",
      "name": "Mega Matrix Corp",
      "price": 0.235,
      "change_pct": 11.904761904761903,
      "volume": 9,
      "rvol": 0.0,
      "market_cap": 14356282.08,
      "float_shares": 59431195,
      "passed": false,
      "reason": "Filtered: vol 9, vol/float 0.00x < 0.5x, avg $vol $0.1M < $0.5M"
    },
    {
      "ticker": "KUST",
      "name": "Kustom Entertainment Inc",
      "price": 1.07,
      "change_pct": 11.353939015506304,
      "volume": 118197,
      "rvol": 0.0,
      "market_cap": 602349.77,
      "float_shares": 626731,
      "passed": false,
      "reason": "Filtered: mktcap $0.6M, vol/float 0.19x < 0.5x"
    },
    {
      "ticker": "OSUR",
      "name": "Orasure Tech",
      "price": 4.231,
      "change_pct": 11.342105263157896,
      "volume": 12,
      "rvol": 0.0,
      "market_cap": 261624501.4,
      "float_shares": 64268568,
      "passed": false,
      "reason": "Filtered: vol 12, vol/float 0.00x < 0.5x"
    },
    {
      "ticker": "CHNR",
      "name": "China Natural Resources Inc",
      "price": 4.34,
      "change_pct": 11.282051282051281,
      "volume": 8219,
      "rvol": 0.0,
      "market_cap": 4899913.2,
      "float_shares": 567894,
      "passed": false,
      "reason": "Filtered: tiny rvol 0.7x, tiny avg $vol, tiny vol/float 0.01x, vol 8,219, vol/float 0.01x < 0.5x, avg $vol $0.0M < $0.5M"
    },
    {
      "ticker": "NVVE",
      "name": "Nuvve Holding Corp",
      "price": 7.78,
      "change_pct": 10.042432814710041,
      "volume": 8764,
      "rvol": 0.0,
      "market_cap": 3709826.96,
      "float_shares": 416464,
      "passed": false,
      "reason": "Filtered: tiny rvol 0.0x, tiny vol/float 0.02x, vol 8,764, vol/float 0.02x < 0.5x"
    },
    {
      "ticker": "CPIX",
      "name": "Cumberland Pharmaceuticals Inc",
      "price": 8.6,
      "change_pct": 9.554140127388536,
      "volume": 3,
      "rvol": 0.0,
      "market_cap": 117617389.95,
      "float_shares": 8553214,
      "passed": false,
      "reason": "Filtered: vol 3, vol/float 0.00x < 0.5x"
    },
    {
      "ticker": "WLDS",
      "name": "Wearable Devices Ltd.",
      "price": 1.65,
      "change_pct": 9.271523178807941,
      "volume": 212,
      "rvol": 0.0,
      "market_cap": 3306098.19,
      "float_shares": 2183091,
      "passed": false,
      "reason": "Filtered: tiny rvol 0.0x, tiny avg $vol, tiny vol/float 0.00x, vol 212, vol/float 0.00x < 0.5x, avg $vol $0.1M < $0.5M"
    },
    {
      "ticker": "PASW",
      "name": "Ping An Biomedical",
      "price": 0.16,
      "change_pct": 9.06612133605999,
      "volume": 60426,
      "rvol": 0.0,
      "market_cap": 18271485.0,
      "float_shares": 110938200,
      "passed": false,
      "reason": "Filtered: price $0.160, float 110.9M > 100M, vol/float 0.00x < 0.5x, avg $vol $0.0M < $0.5M"
    },
    {
      "ticker": "HKPD",
      "name": "Cellyan Biotechnology Co Ltd",
      "price": 0.413,
      "change_pct": 8.684210526315784,
      "volume": 188,
      "rvol": 0.0,
      "market_cap": 8929994.68,
      "float_shares": 15713668,
      "passed": false,
      "reason": "Filtered: tiny rvol 0.0x, tiny avg $vol, tiny vol/float 0.00x, vol 188, vol/float 0.00x < 0.5x, avg $vol $0.3M < $0.5M"
    },
    {
      "ticker": "AISP",
      "name": "Airship AI Holdings Inc",
      "price": 2.25,
      "change_pct": 8.695652173913052,
      "volume": 429,
      "rvol": 0.0,
      "market_cap": 71289893.34,
      "float_shares": 25087127,
      "passed": false,
      "reason": "Filtered: vol 429, vol/float 0.00x < 0.5x"
    },
    {
      "ticker": "VBIO",
      "name": "Valion Bio Inc",
      "price": 0.338,
      "change_pct": 8.681672025723481,
      "volume": 3034,
      "rvol": 0.0,
      "market_cap": 1291041.55,
      "float_shares": 4012513,
      "passed": false,
      "reason": "Filtered: tiny rvol 0.0x, tiny avg $vol, tiny vol/float 0.00x, vol 3,034, vol/float 0.00x < 0.5x, avg $vol $0.2M < $0.5M"
    },
    {
      "ticker": "NTCL",
      "name": "Netclass Technology Inc.",
      "price": 3.482,
      "change_pct": 8.473520249221192,
      "volume": 49,
      "rvol": 0.0,
      "market_cap": 4233534.18,
      "float_shares": 1077960,
      "passed": false,
      "reason": "Filtered: tiny rvol 0.0x, tiny avg $vol, tiny vol/float 0.00x, vol 49, vol/float 0.00x < 0.5x, avg $vol $0.2M < $0.5M"
    },
    {
      "ticker": "MYND",
      "name": "Mynd.ai, Inc.",
      "price": 0.435,
      "change_pct": 8.370702541106134,
      "volume": 110,
      "rvol": 0.0,
      "market_cap": 18923844.45,
      "float_shares": 46605517,
      "passed": false,
      "reason": "Filtered: vol 110, vol/float 0.00x < 0.5x, avg $vol $0.0M < $0.5M"
    },
    {
      "ticker": "CHGG",
      "name": "Chegg Inc",
      "price": 1.0,
      "change_pct": 8.108108108108103,
      "volume": 184,
      "rvol": 0.0,
      "market_cap": 103561925.15,
      "float_shares": 107619823,
      "passed": false,
      "reason": "Filtered: vol 184, float 107.6M > 100M, vol/float 0.00x < 0.5x"
    },
    {
      "ticker": "SKM",
      "name": "Sk Telecom",
      "price": 34.3,
      "change_pct": 7.3552425665101655,
      "volume": 10295,
      "rvol": 0.0,
      "market_cap": 12352477113.9,
      "float_shares": 386515891,
      "passed": false,
      "reason": "Filtered: mktcap $12352.5M, vol 10,295, float 386.5M > 100M, vol/float 0.00x < 0.5x"
    },
    {
      "ticker": "AIDX",
      "name": "20/20 Biolabs Inc",
      "price": 0.585,
      "change_pct": 6.790799561883902,
      "volume": 2011,
      "rvol": 0.0,
      "market_cap": 5812995.04,
      "float_shares": 10611528,
      "passed": false,
      "reason": "Filtered: tiny rvol 0.0x, tiny avg $vol, tiny vol/float 0.00x, vol 2,011, vol/float 0.00x < 0.5x, avg $vol $0.1M < $0.5M"
    },
    {
      "ticker": "ADAM",
      "name": "Adamas Trust Inc",
      "price": 9.47,
      "change_pct": 7.005649717514135,
      "volume": 723,
      "rvol": 0.0,
      "market_cap": 795270805.8,
      "float_shares": 83075853,
      "passed": false,
      "reason": "Filtered: vol 723, vol/float 0.00x < 0.5x"
    },
    {
      "ticker": "GRMN",
      "name": "Garmin",
      "price": 253.0,
      "change_pct": 6.908937249102047,
      "volume": 1,
      "rvol": 0.0,
      "market_cap": 45639421149.9,
      "float_shares": 164258663,
      "passed": false,
      "reason": "Filtered: price $253.000, mktcap $45639.4M, vol 1, float 164.3M > 100M, vol/float 0.00x < 0.5x"
    },
    {
      "ticker": "APUS",
      "name": "APIMEDS PHARMACEUTICALS US INC",
      "price": 0.68,
      "change_pct": 6.7503924646781845,
      "volume": 5,
      "rvol": 0.0,
      "market_cap": 9613079.75,
      "float_shares": 6231927,
      "passed": false,
      "reason": "Filtered: tiny rvol 0.0x, tiny avg $vol, tiny vol/float 0.00x, vol 5, vol/float 0.00x < 0.5x, avg $vol $0.1M < $0.5M"
    },
    {
      "ticker": "ACTU",
      "name": "Actuate Therapeutics Inc",
      "price": 1.44,
      "change_pct": 6.666666666666655,
      "volume": 1,
      "rvol": 0.0,
      "market_cap": 32299900.2,
      "float_shares": 20376552,
      "passed": false,
      "reason": "Filtered: vol 1, vol/float 0.00x < 0.5x"
    },
    {
      "ticker": "JYD",
      "name": "Jayud Global Logistics Limited",
      "price": 0.799,
      "change_pct": 6.647090229578226,
      "volume": 43,
      "rvol": 0.0,
      "market_cap": 6217535.88,
      "float_shares": 6680452,
      "passed": false,
      "reason": "Filtered: tiny rvol 0.0x, tiny avg $vol, tiny vol/float 0.00x, vol 43, vol/float 0.00x < 0.5x, avg $vol $0.3M < $0.5M"
    },
    {
      "ticker": "ZKIN",
      "name": "ZK International Group",
      "price": 1.46,
      "change_pct": 6.5693430656934195,
      "volume": 1,
      "rvol": 0.0,
      "market_cap": 78517861.96,
      "float_shares": 56292897,
      "passed": false,
      "reason": "Filtered: vol 1, vol/float 0.00x < 0.5x, avg $vol $0.0M < $0.5M"
    },
    {
      "ticker": "BGL",
      "name": "Blue Gold Limited",
      "price": 0.221,
      "change_pct": 6.608779546550887,
      "volume": 960,
      "rvol": 0.0,
      "market_cap": 8976447.18,
      "float_shares": 23390201,
      "passed": false,
      "reason": "Filtered: tiny rvol 0.0x, tiny avg $vol, tiny vol/float 0.00x, vol 960, vol/float 0.00x < 0.5x, avg $vol $0.1M < $0.5M"
    },
    {
      "ticker": "JSPR",
      "name": "Jasper Therapeutics Inc",
      "price": 0.82,
      "change_pct": 6.493506493506485,
      "volume": 100,
      "rvol": 0.0,
      "market_cap": 25621411.97,
      "float_shares": 32941251,
      "passed": false,
      "reason": "Filtered: vol 100, vol/float 0.00x < 0.5x"
    },
    {
      "ticker": "CULP",
      "name": "Culp Inc",
      "price": 3.94,
      "change_pct": 6.48648648648648,
      "volume": 100,
      "rvol": 0.0,
      "market_cap": 46852300.8,
      "float_shares": 11268799,
      "passed": false,
      "reason": "Filtered: vol 100, vol/float 0.00x < 0.5x, avg $vol $0.2M < $0.5M"
    },
    {
      "ticker": "BOXL",
      "name": "Boxlight Corp",
      "price": 3.8,
      "change_pct": 6.442577030812324,
      "volume": 125,
      "rvol": 0.0,
      "market_cap": 2381015.07,
      "float_shares": 525697,
      "passed": false,
      "reason": "Filtered: tiny rvol 0.0x, tiny avg $vol, tiny vol/float 0.00x, vol 125, vol/float 0.00x < 0.5x, avg $vol $0.1M < $0.5M"
    },
    {
      "ticker": "CVGI",
      "name": "Commercial Veh Group Inc",
      "price": 5.19,
      "change_pct": 6.3524590163934525,
      "volume": 10,
      "rvol": 0.0,
      "market_cap": 178225866.72,
      "float_shares": 30119735,
      "passed": false,
      "reason": "Filtered: vol 10, vol/float 0.00x < 0.5x"
    },
    {
      "ticker": "MRLN",
      "name": "Merlin Inc",
      "price": 4.073,
      "change_pct": 6.344647519582254,
      "volume": 1,
      "rvol": 0.0,
      "market_cap": 323805653.31,
      "float_shares": 75786224,
      "passed": false,
      "reason": "Filtered: vol 1, vol/float 0.00x < 0.5x"
    },
    {
      "ticker": "SABS",
      "name": "SAB BIOTHERAPEUTICS INC",
      "price": 3.87,
      "change_pct": 6.318681318681318,
      "volume": 27,
      "rvol": 0.0,
      "market_cap": 278329302.16,
      "float_shares": 69389551,
      "passed": false,
      "reason": "Filtered: vol 27, vol/float 0.00x < 0.5x"
    },
    {
      "ticker": "ANPA",
      "name": "Rich Sparkle Holdings Limited",
      "price": 4.25,
      "change_pct": 6.25,
      "volume": 16,
      "rvol": 0.0,
      "market_cap": 60407020.0,
      "float_shares": 4391755,
      "passed": false,
      "reason": "Filtered: vol 16, vol/float 0.00x < 0.5x, avg $vol $0.0M < $0.5M"
    },
    {
      "ticker": "CMMB",
      "name": "Chemomab Therapeutics Ltd",
      "price": 1.56,
      "change_pct": 6.122448979591842,
      "volume": 1,
      "rvol": 0.0,
      "market_cap": 10771660.2,
      "float_shares": 6515175,
      "passed": false,
      "reason": "Filtered: vol 1, vol/float 0.00x < 0.5x, avg $vol $0.2M < $0.5M"
    },
    {
      "ticker": "SILO",
      "name": "Silo Pharma Inc",
      "price": 4.998,
      "change_pct": 6.114649681528668,
      "volume": 1,
      "rvol": 0.0,
      "market_cap": 5315753.1,
      "float_shares": 923114,
      "passed": false,
      "reason": "Filtered: tiny rvol 0.0x, tiny vol/float 0.00x, vol 1, vol/float 0.00x < 0.5x"
    },
    {
      "ticker": "NFE",
      "name": "New Fortress Energy",
      "price": 0.36,
      "change_pct": 6.007067137809179,
      "volume": 1008,
      "rvol": 0.0,
      "market_cap": 97001527.14,
      "float_shares": 179499771,
      "passed": false,
      "reason": "Filtered: vol 1,008, float 179.5M > 100M, vol/float 0.00x < 0.5x"
    },
    {
      "ticker": "AEMD",
      "name": "Aethlon Medical",
      "price": 0.647,
      "change_pct": 6.065573770491809,
      "volume": 151,
      "rvol": 0.0,
      "market_cap": 1606471.6,
      "float_shares": 2498022,
      "passed": false,
      "reason": "Filtered: tiny rvol 0.0x, tiny avg $vol, tiny vol/float 0.00x, vol 151, vol/float 0.00x < 0.5x, avg $vol $0.1M < $0.5M"
    },
    {
      "ticker": "JFU",
      "name": "9F Inc.",
      "price": 2.36,
      "change_pct": 6.019766397124883,
      "volume": 15,
      "rvol": 0.0,
      "market_cap": 26207439.26,
      "float_shares": 4622590,
      "passed": false,
      "reason": "Filtered: vol 15, vol/float 0.00x < 0.5x, avg $vol $0.0M < $0.5M"
    },
    {
      "ticker": "SNTG",
      "name": "Sentage Holdings Inc",
      "price": 2.211,
      "change_pct": 5.7894736842105265,
      "volume": 528356,
      "rvol": 0.0,
      "market_cap": 5863129.25,
      "float_shares": 1059325,
      "passed": false,
      "reason": "Filtered: tiny rvol 0.9x, tiny vol/float 0.50x, vol/float 0.50x < 0.5x"
    },
    {
      "ticker": "FULC",
      "name": "Fulcrum Therapeutics",
      "price": 3.89,
      "change_pct": 5.706521739130434,
      "volume": 54,
      "rvol": 0.0,
      "market_cap": 245210621.28,
      "float_shares": 64043457,
      "passed": false,
      "reason": "Filtered: vol 54, vol/float 0.00x < 0.5x"
    }
  ],
  "all_losers": [
    {
      "ticker": "OMH",
      "name": "Ohmyhome Limited",
      "price": 0.456,
      "change_pct": -43.431336062523265,
      "volume": 175460,
      "rvol": 0.0,
      "market_cap": 18621821.0,
      "float_shares": 0,
      "passed": false,
      "reason": "Bounce scanner disabled"
    },
    {
      "ticker": "JZXN",
      "name": "Jiuzi Holdings Inc",
      "price": 1.32,
      "change_pct": -31.606217616580306,
      "volume": 24463,
      "rvol": 0.0,
      "market_cap": 2564663.0,
      "float_shares": 0,
      "passed": false,
      "reason": "Bounce scanner disabled"
    },
    {
      "ticker": "LBGJ",
      "name": "Li Bang International Corporation Inc.",
      "price": 0.041,
      "change_pct": -31.552587646076795,
      "volume": 4314942,
      "rvol": 0.0,
      "market_cap": 201168.0,
      "float_shares": 0,
      "passed": false,
      "reason": "Bounce scanner disabled"
    },
    {
      "ticker": "PMI",
      "name": "Picard Medical, Inc.",
      "price": 0.085,
      "change_pct": -29.460580912863065,
      "volume": 583352,
      "rvol": 0.0,
      "market_cap": 12374860.0,
      "float_shares": 0,
      "passed": false,
      "reason": "Bounce scanner disabled"
    },
    {
      "ticker": "FFAI",
      "name": "Faraday Future Intelligent Electric Inc",
      "price": 0.081,
      "change_pct": -27.41935483870968,
      "volume": 324571,
      "rvol": 0.0,
      "market_cap": 40654802.0,
      "float_shares": 0,
      "passed": false,
      "reason": "Bounce scanner disabled"
    },
    {
      "ticker": "ZYBT",
      "name": "Zhengye Biotechnology Holding Limited",
      "price": 2.2,
      "change_pct": -22.807017543859644,
      "volume": 134446,
      "rvol": 0.0,
      "market_cap": 84716250.0,
      "float_shares": 0,
      "passed": false,
      "reason": "Bounce scanner disabled"
    },
    {
      "ticker": "VTAK",
      "name": "Catheter Precision",
      "price": 0.4,
      "change_pct": -19.01194573800364,
      "volume": 8191,
      "rvol": 0.0,
      "market_cap": 1782717.0,
      "float_shares": 0,
      "passed": false,
      "reason": "Bounce scanner disabled"
    },
    {
      "ticker": "CPHI",
      "name": "China Pharma",
      "price": 6.6,
      "change_pct": -18.51851851851852,
      "volume": 765518,
      "rvol": 0.0,
      "market_cap": 328228216.0,
      "float_shares": 0,
      "passed": false,
      "reason": "Bounce scanner disabled"
    },
    {
      "ticker": "SLGB",
      "name": "Smart Logistics Global Limited",
      "price": 0.813,
      "change_pct": -17.032350239820396,
      "volume": 114344,
      "rvol": 0.0,
      "market_cap": 44095500.0,
      "float_shares": 0,
      "passed": false,
      "reason": "Bounce scanner disabled"
    },
    {
      "ticker": "PEGA",
      "name": "Pegasystems Inc",
      "price": 26.18,
      "change_pct": -15.384615384615389,
      "volume": 27211,
      "rvol": 0.0,
      "market_cap": 5170570617.0,
      "float_shares": 0,
      "passed": false,
      "reason": "Bounce scanner disabled"
    },
    {
      "ticker": "VIVK",
      "name": "Vivakor",
      "price": 2.16,
      "change_pct": -16.279069767441857,
      "volume": 98394,
      "rvol": 0.0,
      "market_cap": 1180762.0,
      "float_shares": 0,
      "passed": false,
      "reason": "Bounce scanner disabled"
    },
    {
      "ticker": "BYAH",
      "name": "PARK HA BIOLOGICAL TECHNOLOGY",
      "price": 0.435,
      "change_pct": -14.93938208838482,
      "volume": 4218,
      "rvol": 0.0,
      "market_cap": 3227555.0,
      "float_shares": 0,
      "passed": false,
      "reason": "Bounce scanner disabled"
    },
    {
      "ticker": "VEEE",
      "name": "Twin Vee Powercats Co",
      "price": 22.6,
      "change_pct": -13.9047619047619,
      "volume": 4349,
      "rvol": 0.0,
      "market_cap": 13894912.0,
      "float_shares": 0,
      "passed": false,
      "reason": "Bounce scanner disabled"
    },
    {
      "ticker": "TRIB",
      "name": "Trinity Biotech Plc",
      "price": 0.31,
      "change_pct": -13.576805129634797,
      "volume": 110,
      "rvol": 0.0,
      "market_cap": 7263986.0,
      "float_shares": 0,
      "passed": false,
      "reason": "Bounce scanner disabled"
    },
    {
      "ticker": "SGLY",
      "name": "Singularity Future Tech Ltd",
      "price": 0.231,
      "change_pct": -12.96156744536549,
      "volume": 31,
      "rvol": 0.0,
      "market_cap": 1935692.0,
      "float_shares": 0,
      "passed": false,
      "reason": "Bounce scanner disabled"
    },
    {
      "ticker": "SDOT",
      "name": "Sadot Group",
      "price": 19.2,
      "change_pct": -12.168344007319305,
      "volume": 3435,
      "rvol": 0.0,
      "market_cap": 16263840.0,
      "float_shares": 0,
      "passed": false,
      "reason": "Bounce scanner disabled"
    },
    {
      "ticker": "CHR",
      "name": "Cheer Holding",
      "price": 1.75,
      "change_pct": -12.060301507537687,
      "volume": 45858,
      "rvol": 0.0,
      "market_cap": 4103616.0,
      "float_shares": 0,
      "passed": false,
      "reason": "Bounce scanner disabled"
    },
    {
      "ticker": "JUNS",
      "name": "JUPITER NEUROSCIENCES, INC.",
      "price": 0.15,
      "change_pct": -11.608721272834412,
      "volume": 928253,
      "rvol": 0.0,
      "market_cap": 8183631.0,
      "float_shares": 0,
      "passed": false,
      "reason": "Bounce scanner disabled"
    },
    {
      "ticker": "ADTN",
      "name": "Adtran Inc",
      "price": 10.79,
      "change_pct": -11.12026359143329,
      "volume": 8951,
      "rvol": 0.0,
      "market_cap": 983316934.0,
      "float_shares": 0,
      "passed": false,
      "reason": "Bounce scanner disabled"
    },
    {
      "ticker": "ZNB",
      "name": "Zeta Network Group",
      "price": 0.334,
      "change_pct": -11.075612353567617,
      "volume": 63589,
      "rvol": 0.0,
      "market_cap": 696005.0,
      "float_shares": 0,
      "passed": false,
      "reason": "Bounce scanner disabled"
    },
    {
      "ticker": "RCON",
      "name": "Recon Technology Ltd",
      "price": 0.383,
      "change_pct": -10.784998835313301,
      "volume": 19937,
      "rvol": 0.0,
      "market_cap": 38906353.0,
      "float_shares": 0,
      "passed": false,
      "reason": "Bounce scanner disabled"
    },
    {
      "ticker": "GSUN",
      "name": "Golden Sun Health Technology Group Ltd",
      "price": 0.226,
      "change_pct": -10.67193675889328,
      "volume": 196813,
      "rvol": 0.0,
      "market_cap": 2537304.0,
      "float_shares": 0,
      "passed": false,
      "reason": "Bounce scanner disabled"
    },
    {
      "ticker": "DYN",
      "name": "Dyne Therapeutics, Inc.",
      "price": 21.39,
      "change_pct": -10.23919429290809,
      "volume": 495,
      "rvol": 0.0,
      "market_cap": 3939427758.0,
      "float_shares": 0,
      "passed": false,
      "reason": "Bounce scanner disabled"
    },
    {
      "ticker": "QMLS",
      "name": "Qumulusai Inc",
      "price": 6.13,
      "change_pct": -9.985315712187955,
      "volume": 1761,
      "rvol": 0.0,
      "market_cap": 223830610.0,
      "float_shares": 0,
      "passed": false,
      "reason": "Bounce scanner disabled"
    },
    {
      "ticker": "HIHO",
      "name": "Highway Hldgs Ltd",
      "price": 0.964,
      "change_pct": -9.906542056074773,
      "volume": 48097,
      "rvol": 0.0,
      "market_cap": 4950543.0,
      "float_shares": 0,
      "passed": false,
      "reason": "Bounce scanner disabled"
    },
    {
      "ticker": "MSGY",
      "name": "MASONGLORY LTD",
      "price": 0.385,
      "change_pct": -9.411764705882348,
      "volume": 211,
      "rvol": 0.0,
      "market_cap": 6045625.0,
      "float_shares": 0,
      "passed": false,
      "reason": "Bounce scanner disabled"
    },
    {
      "ticker": "GCTK",
      "name": "Glucotrack",
      "price": 0.34,
      "change_pct": -9.309149106428377,
      "volume": 27974,
      "rvol": 0.0,
      "market_cap": 2893898.0,
      "float_shares": 0,
      "passed": false,
      "reason": "Bounce scanner disabled"
    },
    {
      "ticker": "FXHO",
      "name": "Utime Ltd",
      "price": 13.54,
      "change_pct": -8.944182918628112,
      "volume": 481,
      "rvol": 0.0,
      "market_cap": 77285159.0,
      "float_shares": 0,
      "passed": false,
      "reason": "Bounce scanner disabled"
    },
    {
      "ticker": "GIPR",
      "name": "Generation Incom",
      "price": 0.92,
      "change_pct": -8.910891089108908,
      "volume": 9165,
      "rvol": 0.0,
      "market_cap": 1040706.0,
      "float_shares": 0,
      "passed": false,
      "reason": "Bounce scanner disabled"
    },
    {
      "ticker": "BTOG",
      "name": "Bit Origin Limited",
      "price": 0.859,
      "change_pct": -8.820719668824973,
      "volume": 1529,
      "rvol": 0.0,
      "market_cap": 2539105.0,
      "float_shares": 0,
      "passed": false,
      "reason": "Bounce scanner disabled"
    },
    {
      "ticker": "LEDS",
      "name": "Semileds Corp",
      "price": 2.29,
      "change_pct": -8.764940239043815,
      "volume": 1198,
      "rvol": 0.0,
      "market_cap": 20766241.0,
      "float_shares": 0,
      "passed": false,
      "reason": "Bounce scanner disabled"
    },
    {
      "ticker": "OSRH",
      "name": "OSR Health Inc",
      "price": 0.4,
      "change_pct": -8.571428571428566,
      "volume": 23244,
      "rvol": 0.0,
      "market_cap": 15364427.0,
      "float_shares": 0,
      "passed": false,
      "reason": "Bounce scanner disabled"
    },
    {
      "ticker": "RCT",
      "name": "RedCloud",
      "price": 0.22,
      "change_pct": -8.141962421711895,
      "volume": 57573,
      "rvol": 0.0,
      "market_cap": 14217205.0,
      "float_shares": 0,
      "passed": false,
      "reason": "Bounce scanner disabled"
    },
    {
      "ticker": "NXXT",
      "name": "NextNRG Inc.",
      "price": 0.323,
      "change_pct": -7.635115813554476,
      "volume": 42653,
      "rvol": 0.0,
      "market_cap": 58754064.0,
      "float_shares": 0,
      "passed": false,
      "reason": "Bounce scanner disabled"
    },
    {
      "ticker": "CLDX",
      "name": "Celldex Therapeutics Inc",
      "price": 32.9,
      "change_pct": -7.7397644419517615,
      "volume": 5,
      "rvol": 0.0,
      "market_cap": 2799027287.0,
      "float_shares": 0,
      "passed": false,
      "reason": "Bounce scanner disabled"
    },
    {
      "ticker": "MEDS",
      "name": "Datameds AI Inc",
      "price": 3.253,
      "change_pct": -7.58522727272727,
      "volume": 1604,
      "rvol": 0.0,
      "market_cap": 9318136.0,
      "float_shares": 0,
      "passed": false,
      "reason": "Bounce scanner disabled"
    },
    {
      "ticker": "KMRK",
      "name": "K-Tech Solutions Company Limited",
      "price": 1.017,
      "change_pct": -7.545454545454562,
      "volume": 5520,
      "rvol": 0.0,
      "market_cap": 23210000.0,
      "float_shares": 0,
      "passed": false,
      "reason": "Bounce scanner disabled"
    },
    {
      "ticker": "BXBL",
      "name": "Boxabl Incorporated",
      "price": 7.41,
      "change_pct": -7.490636704119846,
      "volume": 3776,
      "rvol": 0.0,
      "market_cap": 82469358.0,
      "float_shares": 0,
      "passed": false,
      "reason": "Bounce scanner disabled"
    },
    {
      "ticker": "NIKI",
      "name": "NIKI BIOSOLUTIONS INC,",
      "price": 8.83,
      "change_pct": -7.442348008385736,
      "volume": 405,
      "rvol": 0.0,
      "market_cap": 7769147.0,
      "float_shares": 0,
      "passed": false,
      "reason": "Bounce scanner disabled"
    },
    {
      "ticker": "ITP",
      "name": "It Tech Packaging",
      "price": 0.171,
      "change_pct": -7.517577068685774,
      "volume": 400,
      "rvol": 0.0,
      "market_cap": 3136906.0,
      "float_shares": 0,
      "passed": false,
      "reason": "Bounce scanner disabled"
    },
    {
      "ticker": "BGI",
      "name": "Birks Group",
      "price": 0.529,
      "change_pct": -7.192982456140339,
      "volume": 16250,
      "rvol": 0.0,
      "market_cap": 11168971.0,
      "float_shares": 0,
      "passed": false,
      "reason": "Bounce scanner disabled"
    },
    {
      "ticker": "PFSA",
      "name": "Profusa Inc",
      "price": 1.86,
      "change_pct": -6.999999999999995,
      "volume": 4380,
      "rvol": 0.0,
      "market_cap": 1058686.0,
      "float_shares": 0,
      "passed": false,
      "reason": "Bounce scanner disabled"
    },
    {
      "ticker": "MDCX",
      "name": "Medicus Pharma Ltd",
      "price": 0.361,
      "change_pct": -6.886768119680166,
      "volume": 321,
      "rvol": 0.0,
      "market_cap": 21966370.0,
      "float_shares": 0,
      "passed": false,
      "reason": "Bounce scanner disabled"
    },
    {
      "ticker": "RDGT",
      "name": "RIDGETECH Inc",
      "price": 1.37,
      "change_pct": -6.802721088435365,
      "volume": 12444,
      "rvol": 0.0,
      "market_cap": 1321409.0,
      "float_shares": 0,
      "passed": false,
      "reason": "Bounce scanner disabled"
    },
    {
      "ticker": "LGHL",
      "name": "Lion Group Holding Ltd",
      "price": 1.308,
      "change_pct": -6.571428571428561,
      "volume": 1739,
      "rvol": 0.0,
      "market_cap": 215338.0,
      "float_shares": 0,
      "passed": false,
      "reason": "Bounce scanner disabled"
    },
    {
      "ticker": "GURE",
      "name": "Gulf Resource",
      "price": 3.397,
      "change_pct": -6.5731573157315815,
      "volume": 35,
      "rvol": 0.0,
      "market_cap": 5025366.0,
      "float_shares": 0,
      "passed": false,
      "reason": "Bounce scanner disabled"
    },
    {
      "ticker": "MRNO",
      "name": "Murano Global Investments",
      "price": 0.223,
      "change_pct": -6.538139145012574,
      "volume": 190,
      "rvol": 0.0,
      "market_cap": 19584844.0,
      "float_shares": 0,
      "passed": false,
      "reason": "Bounce scanner disabled"
    },
    {
      "ticker": "SUGP",
      "name": "SU Group Holdings Limited",
      "price": 0.51,
      "change_pct": -6.353286816011745,
      "volume": 4957,
      "rvol": 0.0,
      "market_cap": 2431514.0,
      "float_shares": 0,
      "passed": false,
      "reason": "Bounce scanner disabled"
    },
    {
      "ticker": "COOT",
      "name": "Australian Oilseeds",
      "price": 0.4,
      "change_pct": -6.388953896559792,
      "volume": 1520,
      "rvol": 0.0,
      "market_cap": 12775645.0,
      "float_shares": 0,
      "passed": false,
      "reason": "Bounce scanner disabled"
    },
    {
      "ticker": "VTGN",
      "name": "Vistagen Therapeutics Inc",
      "price": 0.221,
      "change_pct": -5.957446808510633,
      "volume": 1,
      "rvol": 0.0,
      "market_cap": 9642626.0,
      "float_shares": 0,
      "passed": false,
      "reason": "Bounce scanner disabled"
    }
  ],
  "live_quotes": {
    "CHAI": {
      "price": 0.3905,
      "open": 0.4016,
      "high": 0.42,
      "low": 0.3603,
      "close": 0.3905,
      "preClose": 0.45,
      "volume": 13110244,
      "changeRatio": -0.1322,
      "marketValue": 8548765.86,
      "name": "Core AI Holdings Inc",
      "_timestamp": "2026-07-22T08:45:00.955434Z"
    },
    "INLF": {
      "price": 2.23,
      "open": 2.26,
      "high": 2.29,
      "low": 2.12,
      "close": 2.23,
      "preClose": 2.3,
      "volume": 2325339,
      "changeRatio": -0.0304,
      "marketValue": 2439062.5,
      "name": "INLIF",
      "_timestamp": "2026-07-22T08:45:00.955434Z"
    }
  },
  "previous_live_quotes": {
    "ZCMD": {
      "price": 1.47,
      "open": 1.45,
      "high": 1.533,
      "low": 1.4,
      "close": 1.47,
      "preClose": 1.47,
      "volume": 1737371,
      "changeRatio": 0.0,
      "marketValue": 1700122.62,
      "name": "Zhongchao Inc",
      "_timestamp": "2026-07-22T08:42:58.730292Z"
    },
    "CHAI": {
      "price": 0.3905,
      "open": 0.4016,
      "high": 0.42,
      "low": 0.3603,
      "close": 0.3905,
      "preClose": 0.45,
      "volume": 12986900,
      "changeRatio": -0.1322,
      "marketValue": 8548765.86,
      "name": "Core AI Holdings Inc",
      "_timestamp": "2026-07-22T08:42:58.730292Z"
    },
    "INLF": {
      "price": 2.23,
      "open": 2.26,
      "high": 2.29,
      "low": 2.12,
      "close": 2.23,
      "preClose": 2.3,
      "volume": 2272180,
      "changeRatio": -0.0304,
      "marketValue": 2439062.5,
      "name": "INLIF",
      "_timestamp": "2026-07-22T08:42:58.730292Z"
    }
  },
  "scan_stats": {
    "gainers_scanned": 50,
    "losers_scanned": 50,
    "market_status": "PRE-MARKET",
    "market_time": "06:44 PM AEST",
    "market": "us",
    "au_filters": {},
    "us_filters": {}
  }
}